trueloc/__init__.py
trueloc/_version.py
trueloc/cli.py
trueloc/display.py
trueloc/github.py
trueloc/local.py
trueloc/models.py
trueloc/py.typed
trueloc/utils.py
trueloc-0.3.0.dist-info/METADATA
trueloc-0.3.0.dist-info/WHEEL
trueloc-0.3.0.dist-info/entry_points.txt
trueloc-0.3.0.dist-info/licenses/LICENSE
trueloc-0.3.0.dist-info/RECORD
