Metadata-Version: 2.4
Name: trueloc
Version: 0.3.0
Summary: Count lines of code from GitHub pull requests
Author-email: Bas Nijholt <bas@nijho.lt>
License-File: LICENSE
Requires-Python: >=3.12
Requires-Dist: dateparser>=1
Requires-Dist: diskcache>=5
Requires-Dist: httpx>=0.28
Requires-Dist: rich>=13
Requires-Dist: typer>=0.15
